class_mapping/__init__.py
class_mapping/class_loader.py
class_mapping/cls_name_mod.npy
class_mapping/imagenet2012_classes.npy
class_mapping/imagenet21k_classes.npy
class_mapping/imagenet21k_classes_r.npy
class_mapping/val_img_classes_pairs.npy
imagenet_classes-0.1.1.dist-info/licenses/LICENSE
imagenet_classes-0.1.1.dist-info/METADATA
imagenet_classes-0.1.1.dist-info/WHEEL
imagenet_classes-0.1.1.dist-info/top_level.txt
imagenet_classes-0.1.1.dist-info/RECORD
