Metadata-Version: 2.4
Name: imagenet-classes
Version: 0.1.1
Summary: A Python package for managing and retrieving ImageNet-1k mappings among integer class IDs, string class IDs, and human-readable class names.
Home-page: https://github.com/gonikisgo/imagenet-classes
Author: Illia Volkov, Nikita Kisel
Author-email: Illia Volkov <volkoill@cvut.cz>, Nikita Kisel <kiselnik@fel.cvut.cz>
Maintainer-email: Nikita Kisel <kiselnik@fel.cvut.cz>
License: MIT
Project-URL: Homepage, https://github.com/gonikisgo/imagenet-classes
Project-URL: Documentation, https://github.com/gonikisgo/imagenet-classes#readme
Project-URL: Repository, https://github.com/gonikisgo/imagenet-classes
Project-URL: Bug Tracker, https://github.com/gonikisgo/imagenet-classes/issues
Keywords: imagenet,computer-vision,machine-learning,deep-learning,classification
Classifier: Development Status :: 4 - Beta
Classifier: Intended Audience :: Developers
Classifier: Intended Audience :: Science/Research
Classifier: License :: OSI Approved :: MIT License
Classifier: Operating System :: OS Independent
Classifier: Programming Language :: Python :: 3
Classifier: Programming Language :: Python :: 3.8
Classifier: Programming Language :: Python :: 3.9
Classifier: Programming Language :: Python :: 3.10
Classifier: Programming Language :: Python :: 3.11
Classifier: Programming Language :: Python :: 3.12
Classifier: Typing :: Typed
Classifier: Framework :: Pytest
Classifier: Topic :: Scientific/Engineering :: Artificial Intelligence
Classifier: Topic :: Software Development :: Libraries :: Python Modules
Requires-Python: >=3.8
License-File: LICENSE
Requires-Dist: numpy>=1.19.0
Provides-Extra: dev
Requires-Dist: pytest>=6.0; extra == "dev"
Requires-Dist: pytest-cov>=2.0; extra == "dev"
Requires-Dist: black>=21.0; extra == "dev"
Requires-Dist: flake8>=3.8; extra == "dev"
Requires-Dist: mypy>=0.800; extra == "dev"
Dynamic: author
Dynamic: home-page
Dynamic: license-file
Dynamic: requires-python
